README.rst
setup.cfg
setup.py
microbio/__init__.py
microbio.egg-info/PKG-INFO
microbio.egg-info/SOURCES.txt
microbio.egg-info/dependency_links.txt
microbio.egg-info/top_level.txt
microbio/formats/__init__.py
microbio/formats/fast5.py
microbio/formats/fasta.py