Metadata-Version: 1.0
Name: microbio
Version: 0.1.1
Summary: A minimalist Bioinformatics framework
Home-page: https://github.com/grst/microbio
Author: Gregor Sturm
Author-email: gregor.sturm@cs.tum.edu
License: MIT
Keywords: bioinformatics,framework
Platform: UNKNOWN
